strawberry_django_extras/__init__.py
strawberry_django_extras/decorators.py
strawberry_django_extras/exceptions.py
strawberry_django_extras/extensions.py
strawberry_django_extras/field_extensions.py
strawberry_django_extras/functions.py
strawberry_django_extras/inputs.py
strawberry_django_extras/jwt/__init__.py
strawberry_django_extras/jwt/backend.py
strawberry_django_extras/jwt/decorators.py
strawberry_django_extras/jwt/exceptions.py
strawberry_django_extras/jwt/extensions.py
strawberry_django_extras/jwt/middleware.py
strawberry_django_extras/jwt/mutations.py
strawberry_django_extras/jwt/refresh_token/__init__.py
strawberry_django_extras/jwt/refresh_token/apps.py
strawberry_django_extras/jwt/refresh_token/locale/ar/LC_MESSAGES/django.mo
strawberry_django_extras/jwt/refresh_token/locale/ar/LC_MESSAGES/django.po
strawberry_django_extras/jwt/refresh_token/locale/es/LC_MESSAGES/django.mo
strawberry_django_extras/jwt/refresh_token/locale/es/LC_MESSAGES/django.po
strawberry_django_extras/jwt/refresh_token/locale/fr/LC_MESSAGES/django.mo
strawberry_django_extras/jwt/refresh_token/locale/fr/LC_MESSAGES/django.po
strawberry_django_extras/jwt/refresh_token/locale/nl/LC_MESSAGES/django.mo
strawberry_django_extras/jwt/refresh_token/locale/nl/LC_MESSAGES/django.po
strawberry_django_extras/jwt/refresh_token/locale/pt_BR/LC_MESSAGES/django.mo
strawberry_django_extras/jwt/refresh_token/locale/pt_BR/LC_MESSAGES/django.po
strawberry_django_extras/jwt/refresh_token/management/__init__.py
strawberry_django_extras/jwt/refresh_token/management/commands/__init__.py
strawberry_django_extras/jwt/refresh_token/management/commands/cleartokens.py
strawberry_django_extras/jwt/refresh_token/managers.py
strawberry_django_extras/jwt/refresh_token/migrations/0001_initial.py
strawberry_django_extras/jwt/refresh_token/migrations/__init__.py
strawberry_django_extras/jwt/refresh_token/models.py
strawberry_django_extras/jwt/refresh_token/shortcuts.py
strawberry_django_extras-0.2.6.dist-info/METADATA
strawberry_django_extras-0.2.6.dist-info/WHEEL
strawberry_django_extras-0.2.6.dist-info/licenses/LICENSE
strawberry_django_extras-0.2.6.dist-info/RECORD
